flon/__init__.py
flon/basket.py
flon/exceptions.py
flon/parse.py
flon/tokenize.py
flon-0.2.0.dist-info/WHEEL
flon-0.2.0.dist-info/METADATA
flon-0.2.0.dist-info/RECORD
